libdoc2json/__init__.py
libdoc2json/__main__.py
libdoc2json/libdoc2json.py
robotframework_libdoc2json-0.4.dist-info/LICENSE
robotframework_libdoc2json-0.4.dist-info/METADATA
robotframework_libdoc2json-0.4.dist-info/WHEEL
robotframework_libdoc2json-0.4.dist-info/top_level.txt
robotframework_libdoc2json-0.4.dist-info/RECORD
