Metadata-Version: 2.1
Name: robotframework-libdoc2json
Version: 0.4
Summary: A python module to create json for VSCode Robot Framework Intellisense.
Home-page: https://github.com/Snooz82/robotframework-LibDoc2Json
Author: René Rohner(Snooz82)
Author-email: snooz@posteo.de
License: UNKNOWN
Platform: UNKNOWN
Classifier: Programming Language :: Python :: 3
Classifier: Programming Language :: Python :: 3.7
Classifier: License :: OSI Approved :: Apache Software License
Classifier: Operating System :: OS Independent
Classifier: Topic :: Software Development :: Testing
Classifier: Topic :: Software Development :: Testing :: Acceptance
Classifier: Framework :: Robot Framework
Requires-Python: >3.6
Requires-Dist: robotframework (>=3.1)
